lugat/__init__.py
lugat/__main__.py
lugat/__version__.py
lugat/alfred.py
lugat/args.py
lugat/cli.py
lugat/colorize.py
lugat/dict.py
lugat/word.py
lugat-0.2.0.dist-info/LICENSE
lugat-0.2.0.dist-info/METADATA
lugat-0.2.0.dist-info/WHEEL
lugat-0.2.0.dist-info/entry_points.txt
lugat-0.2.0.dist-info/top_level.txt
lugat-0.2.0.dist-info/zip-safe
lugat-0.2.0.dist-info/RECORD
