Metadata-Version: 2.1
Name: lugat
Version: 0.2.0
Summary: TDK Güncel Türkçe Sözlük için komut satırı uygulaması.
Home-page: https://github.com/ademozay/lugat
Author: Adem Özay
Author-email: ozayadem@gmail.com
License: UNKNOWN
Keywords: tdk,cli
Platform: UNKNOWN
Requires-Dist: requests (>=2.0.0)
Requires-Dist: termcolor (>=1.0.0)
